json_justify/__init__.py
json_justify/fields.py
json_justify/jason.py
json_justify/utils.py
json_justify/validators.py
justify-0.3.dist-info/METADATA
justify-0.3.dist-info/WHEEL
justify-0.3.dist-info/top_level.txt
justify-0.3.dist-info/RECORD
