Metadata-Version: 2.1
Name: justify
Version: 0.3
Summary: An art of writing json
Home-page: https://github.com/AngrySoilder/json-justify
Author: Akash Chaudhari
Author-email: chaudharia041@gmail.com
License: MIT
Platform: UNKNOWN
Classifier: Programming Language :: Python :: 3.6
Classifier: Programming Language :: Python :: 3.5
Classifier: License :: OSI Approved :: MIT License
Classifier: Operating System :: OS Independent
Requires-Dist: email-validator
